pymates/__init__.py
pymates/console.py
pymates/fem.png
pymates/gg.mp3
pymates/history.py
pymates/hp.png
pymates/hp_backup.png
pymates/main.py
pymates/mons.py
pymates/pokeutil.py
pymates/tests.py
pymates/windows.py
pymates/tests/1.png
pymates/tests/10.png
pymates/tests/2.png
pymates/tests/3.png
pymates/tests/4.png
pymates/tests/5.png
pymates/tests/6.png
pymates/tests/7.png
pymates/tests/8.png
pymates/tests/9.png
pymates-1.0.11.dist-info/METADATA
pymates-1.0.11.dist-info/WHEEL
pymates-1.0.11.dist-info/entry_points.txt
pymates-1.0.11.dist-info/top_level.txt
pymates-1.0.11.dist-info/RECORD
