Metadata-Version: 2.1
Name: pymates
Version: 1.0.11
Author: Matt Harris
Author-email: WorkMatthewJHarris94@gmail.com
License: MIT
Classifier: Programming Language :: Python :: 3
Classifier: License :: OSI Approved :: MIT License
Classifier: Operating System :: OS Independent
Requires-Dist: humanize
Requires-Dist: numpy
Requires-Dist: pillow
Requires-Dist: pytesseract
